[
  {"data":"การค้นพบที่สำคัญคือลิงชิมแปนซีมีบุคลิกภาพ ความคิด และอารมณ์ที่คล้ายคลึงกับมนุษย์ รวมถึงมีพันธุกรรม DNA ที่ต่างจากมนุษย์เพียงประมาณ 1% เท่านั้น"},
  {"data":"ร่างกายเปรียบเสมือนรังของโรคที่สะสมแบคทีเรียและสิ่งสกปรกมาตลอดทั้งวัน การอาบน้ำจะช่วยลดการสะสมแบคทีเรียได้ถึงร้อยละ 32"},
  {"data":"การอาบน้ำผิดวิธีหรือผิดเวลาส่งผลให้ร่างกายแก่เร็ว เนื่องจากฮอร์โมนที่ช่วยซ่อมแซมร่างกายทำงานได้ไม่เต็มประสิทธิภาพ"},
  {"data":"อุปกรณ์กำจัดวัชพืชแบบด้ามยาวช่วยให้ทำงานขณะยืนได้และไม่ทำลายหน้าดินเหมือนเครื่องจักร"},
  {"data":"วิธีการหลอกลวงจะใช้การเชื่อมโยงเรื่องกรรมจากอดีตชาติมาสร้างความกังวลใจ เพื่อให้ผู้เสียหายยอมจ่ายเงินทำบุญแก้กรรม"},
  {"data":"การเช่าที่ดินทำกินช่วยให้เราไม่ต้องเป็นหนี้ก้อนโต และสามารถหมุนเวียนไปเริ่มใหม่ที่อื่นได้เมื่อหมดสัญญา"},
  {"data":"โดนัลด์ ทรัมป์ ประกาศถอนตัวออกจากสนธิสัญญาด้านภูมิอากาศที่สำคัญซึ่งส่งผลกระทบต่อความร่วมมือด้านสิ่งแวดล้อมโลก"}
]